dji_geotagger/__init__.py
dji_geotagger/config/default_ppk_dict.py
dji_geotagger/config/import_config.py
dji_geotagger/core/PPP_sum_parser.py
dji_geotagger/core/__init__.py
dji_geotagger/core/camera_pos_solver.py
dji_geotagger/core/exif_parser.py
dji_geotagger/core/mrk_parser.py
dji_geotagger/core/pos_parser.py
dji_geotagger/ppk/__init__.py
dji_geotagger/ppk/ephemeris_downloader.py
dji_geotagger/ppk/ppk_solver.py
dji_geotagger/ppk/raw_converter.py
dji_geotagger/tools/install_utils.py
dji_geotagger/tools/tools.py
dji_geotagger/tools/RTKLIB/bin/__init__.py
dji_geotagger-1.0.11.dist-info/licenses/LICENSE
temp/__init__.py
dji_geotagger-1.0.11.dist-info/METADATA
dji_geotagger-1.0.11.dist-info/WHEEL
dji_geotagger-1.0.11.dist-info/top_level.txt
dji_geotagger-1.0.11.dist-info/RECORD
