Metadata-Version: 2.4
Name: dji-geotagger
Version: 1.0.11
Summary: A precise PPK + MRK-based geotagging tool for DJI RTK drones
Author-email: Ray Pan <hungwei.pan2@ucalgary.ca>
License: BSD-2-Clause
Project-URL: Homepage, https://github.com/RayPan-UC/dji-geotagger
Classifier: Programming Language :: Python :: 3
Classifier: License :: OSI Approved :: BSD License
Classifier: Operating System :: OS Independent
Classifier: Topic :: Scientific/Engineering :: GIS
Classifier: Topic :: Scientific/Engineering :: Image Recognition
Requires-Python: >=3.9
License-File: LICENSE
Requires-Dist: pillow
Requires-Dist: defusedxml
Requires-Dist: pandas
Requires-Dist: numpy
Requires-Dist: pyproj
Requires-Dist: tqdm
Dynamic: license-file
